odoo/addons/hr_expense_type/README.rst
odoo/addons/hr_expense_type/__init__.py
odoo/addons/hr_expense_type/__manifest__.py
odoo/addons/hr_expense_type/i18n/es.po
odoo/addons/hr_expense_type/i18n/hr_expense_type.pot
odoo/addons/hr_expense_type/i18n/it.po
odoo/addons/hr_expense_type/models/__init__.py
odoo/addons/hr_expense_type/models/hr_expense.py
odoo/addons/hr_expense_type/models/hr_expense_type.py
odoo/addons/hr_expense_type/readme/CONTRIBUTORS.rst
odoo/addons/hr_expense_type/readme/DESCRIPTION.rst
odoo/addons/hr_expense_type/readme/USAGE.rst
odoo/addons/hr_expense_type/security/ir.model.access.csv
odoo/addons/hr_expense_type/static/description/icon.png
odoo/addons/hr_expense_type/static/description/index.html
odoo/addons/hr_expense_type/views/hr_expense_type_views.xml
odoo/addons/hr_expense_type/views/hr_expense_views.xml
odoo12_addon_hr_expense_type-12.0.1.0.0.99.dev7.dist-info/METADATA
odoo12_addon_hr_expense_type-12.0.1.0.0.99.dev7.dist-info/WHEEL
odoo12_addon_hr_expense_type-12.0.1.0.0.99.dev7.dist-info/top_level.txt
odoo12_addon_hr_expense_type-12.0.1.0.0.99.dev7.dist-info/RECORD
